Metadata-Version: 1.0
Name: git-bump-version
Version: 2.0.0
Summary: Automatically bumps version based on last tag and current branch
Home-page: https://github.com/silent-snowman/git_bump_version
Author: Nathan Grubb
Author-email: mrnathangrubb@gmail.com
License: UNKNOWN
Keywords: git,tag,version
Platform: UNKNOWN
